evileye/__init__.py
evileye/cli.py
evileye/cli_wrapper.py
evileye/configure.py
evileye/configure_wrapper.py
evileye/credentials.json
evileye/credentials_proto.json
evileye/database_config.json
evileye/launch.py
evileye/launch_wrapper.py
evileye/process.py
evileye/process_wrapper.py
evileye/run_config_helper.py
evileye/server.py
evileye/server_wrapper.py
evileye/api/__init__.py
evileye/api/app.py
evileye/api/core/__init__.py
evileye/api/core/broker_access.py
evileye/api/core/config_run_access.py
evileye/api/core/config_run_manager.py
evileye/api/core/frame_broker.py
evileye/api/core/manager_access.py
evileye/api/core/pipeline_manager.py
evileye/api/routes/__init__.py
evileye/api/routes/configs.py
evileye/api/routes/events.py
evileye/api/routes/pipelines.py
evileye/api/routes/streaming.py
evileye/attributes_detection/__init__.py
evileye/attributes_detection/attribute_classifier.py
evileye/attributes_detection/attribute_detection_thread.py
evileye/attributes_detection/attribute_detector.py
evileye/attributes_detection/roi_feeder.py
evileye/capture/__init__.py
evileye/capture/video_capture_base.py
evileye/capture/video_capture_gstreamer.py
evileye/capture/video_capture_opencv.py
evileye/controller/__init__.py
evileye/controller/controller.py
evileye/core/__init__.py
evileye/core/base_class.py
evileye/core/class_manager.py
evileye/core/frame.py
evileye/core/gui_events.py
evileye/core/logger.py
evileye/core/logging_config.py
evileye/core/mp_control.py
evileye/core/mp_worker.py
evileye/core/pipeline_base.py
evileye/core/pipeline_processors.py
evileye/core/pipeline_simple.py
evileye/core/processor_base.py
evileye/core/processor_frame.py
evileye/core/processor_source.py
evileye/core/processor_step.py
evileye/core/storage_monitor.py
evileye/database/config_history_manager.py
evileye/database_controller/__init__.py
evileye/database_controller/database_controller_base.py
evileye/database_controller/database_controller_pg.py
evileye/database_controller/db_adapter.py
evileye-0.0.9.dist-info/licenses/LICENSE
evileye-0.0.9.dist-info/METADATA
evileye-0.0.9.dist-info/WHEEL
evileye-0.0.9.dist-info/entry_points.txt
evileye-0.0.9.dist-info/top_level.txt
evileye-0.0.9.dist-info/RECORD
