Metadata-Version: 2.4
Name: evileye
Version: 0.0.9
Summary: Intelligence video surveillance system
Author-email: AI Community <palexab@gmail.com>
Maintainer-email: AI Community <palexab@gmail.com>
License-Expression: MIT
Project-URL: Homepage, https://github.com/evileye/evileye
Project-URL: Documentation, https://evileye.readthedocs.io/
Project-URL: Repository, https://github.com/evileye/evileye.git
Project-URL: Bug Tracker, https://github.com/evileye/evileye/issues
Project-URL: Source Code, https://github.com/evileye/evileye
Keywords: surveillance,computer-vision,object-detection,object-tracking,video-processing
Classifier: Development Status :: 4 - Beta
Classifier: Intended Audience :: Developers
Classifier: Intended Audience :: Science/Research
Classifier: Operating System :: OS Independent
Classifier: Programming Language :: Python :: 3
Classifier: Programming Language :: Python :: 3.10
Classifier: Programming Language :: Python :: 3.11
Classifier: Topic :: Scientific/Engineering :: Artificial Intelligence
Classifier: Topic :: Scientific/Engineering :: Image Processing
Classifier: Topic :: Software Development :: Libraries :: Python Modules
Requires-Python: >=3.10
License-File: LICENSE
Requires-Dist: ultralytics>=8.0.0
Requires-Dist: psycopg2-binary>=2.9.0
Requires-Dist: lapx>=0.1.0
Requires-Dist: albumentations>=1.3.0
Requires-Dist: shapely>=2.0.0
Requires-Dist: scikit-learn>=1.3.0
Requires-Dist: onnxruntime-gpu>=1.15.0; platform_system != "Windows"
Requires-Dist: onnxruntime-gpu<1.20.2,>=1.15.0; platform_system == "Windows"
Requires-Dist: tqdm>=4.65.0
Requires-Dist: pympler>=0.9.0
Requires-Dist: opencv-python>=4.8.0
Requires-Dist: opencv-contrib-python>=4.8.0
Requires-Dist: numpy>=1.24.0
Requires-Dist: pillow>=10.0.0
Requires-Dist: pyyaml>=6.0
Requires-Dist: matplotlib>=3.7.0
Requires-Dist: seaborn>=0.12.0
Requires-Dist: pandas>=2.0.0
Requires-Dist: sqlalchemy>=2.0.0
Requires-Dist: psutil>=5.9.0
Requires-Dist: requests>=2.31.0
Requires-Dist: websockets>=11.0.0
Requires-Dist: aiohttp>=3.8.0
Requires-Dist: asyncio-mqtt>=0.13.0
Requires-Dist: pydantic>=2.0.0
Requires-Dist: fastapi>=0.115.0
Requires-Dist: uvicorn>=0.30.0
Requires-Dist: loguru>=0.7.0
Requires-Dist: rich>=13.0.0
Requires-Dist: click>=8.1.0
Requires-Dist: typer>=0.9.0
Requires-Dist: PyQt5>=5.15.11; platform_system == "Linux" and platform_machine == "aarch64"
Requires-Dist: PyQt6>=6.5.0; platform_system != "Linux" or platform_machine != "aarch64"
Requires-Dist: rfdetr>=0.1.0
Requires-Dist: supervision>=0.16.0
Provides-Extra: dev
Requires-Dist: pytest>=7.4.0; extra == "dev"
Requires-Dist: pytest-cov>=4.1.0; extra == "dev"
Requires-Dist: pytest-asyncio>=0.21.0; extra == "dev"
Requires-Dist: black>=23.0.0; extra == "dev"
Requires-Dist: isort>=5.12.0; extra == "dev"
Requires-Dist: flake8>=6.0.0; extra == "dev"
Requires-Dist: mypy>=1.5.0; extra == "dev"
Requires-Dist: pre-commit>=3.3.0; extra == "dev"
Requires-Dist: tox>=4.6.0; extra == "dev"
Requires-Dist: sphinx>=7.1.0; extra == "dev"
Requires-Dist: sphinx-rtd-theme>=1.3.0; extra == "dev"
Requires-Dist: myst-parser>=2.0.0; extra == "dev"
Provides-Extra: jetson
Requires-Dist: PyQt5>=5.15.11; extra == "jetson"
Provides-Extra: win
Requires-Dist: onnxruntime<1.20.2; extra == "win"
Dynamic: license-file
